android_inspector/__init__.py
android_inspector/pipelines/__init__.py
android_inspector/pipelines/android_d2d.py
android_inspector/pipes/__init__.py
android_inspector/pipes/android_d2d.py
android_inspector-0.2.0.dist-info/licenses/AUTHORS.rst
android_inspector-0.2.0.dist-info/licenses/CHANGELOG.rst
android_inspector-0.2.0.dist-info/licenses/CODE_OF_CONDUCT.rst
android_inspector-0.2.0.dist-info/licenses/NOTICE
android_inspector-0.2.0.dist-info/licenses/apache-2.0.LICENSE
android_inspector-0.2.0.dist-info/METADATA
android_inspector-0.2.0.dist-info/WHEEL
android_inspector-0.2.0.dist-info/entry_points.txt
android_inspector-0.2.0.dist-info/top_level.txt
android_inspector-0.2.0.dist-info/RECORD
